{"moduleName":null,"summaries":[{"symbol":{"__symbol":0,"members":[]},"metadata":"https://outlook.live.com/owa/?rru=addevent&path=%2fcalendar%2fview%2fMonth&authRedirect=true&realm=live.com&whr=live.com&CBCXT=out&fl=wld"},{"symbol":{"__symbol":1,"members":[]},"metadata":{"__symbolic":"error","message":"Expression form not supported","line":5,"character":37,"fileName":"src/generators/outlook-calendar.generator.ts"}},{"symbol":{"__symbol":2,"members":[]},"metadata":{"__symbolic":"class","extends":{"__symbolic":"resolved","symbol":{"__symbol":3,"members":[]},"line":7,"character":46,"fileName":"src/generators/outlook-calendar.generator.ts"},"members":{"__ctor__":[{"__symbolic":"constructor","parameters":[{"__symbolic":"resolved","symbol":{"__symbol":4,"members":[]},"line":9,"character":33,"fileName":"src/generators/outlook-calendar.generator.ts"}]}]}}}],"symbols":[{"__symbol":0,"name":"OUTLOOK_BASE_URL","filePath":"./outlook-calendar.generator"},{"__symbol":1,"name":"DATE_POCTUATION_REGEX","filePath":"./outlook-calendar.generator"},{"__symbol":2,"name":"OutlookCalendarGenerator","filePath":"./outlook-calendar.generator"},{"__symbol":3,"name":"BaseCalendarGenerator","filePath":"./base-calendar.generator"},{"__symbol":4,"name":"ICalendarEvent","filePath":"../model/calendar-event.model"}]}